ssm_transformer/__init__.py
ssm_transformer/ssm_transformer.py
ssm_transformer-0.1.0.dist-info/LICENSE
ssm_transformer-0.1.0.dist-info/METADATA
ssm_transformer-0.1.0.dist-info/WHEEL
ssm_transformer-0.1.0.dist-info/top_level.txt
ssm_transformer-0.1.0.dist-info/RECORD
